openbb_tushare/__init__.py
openbb_tushare/models/__init__.py
openbb_tushare/models/available_indices.py
openbb_tushare/models/balance_sheet.py
openbb_tushare/models/cash_flow.py
openbb_tushare/models/equity_historical.py
openbb_tushare/models/equity_profile.py
openbb_tushare/models/equity_quote.py
openbb_tushare/models/equity_search.py
openbb_tushare/models/historical_dividends.py
openbb_tushare/models/income_statement.py
openbb_tushare/openbb.py
openbb_tushare/provider.py
openbb_tushare/router.py
openbb_tushare/utils/__init__.py
openbb_tushare/utils/ak_helpers.py
openbb_tushare/utils/helpers.py
openbb_tushare/utils/ts_available_indices.py
openbb_tushare/utils/ts_balance_sheet.py
openbb_tushare/utils/ts_cash_flow.py
openbb_tushare/utils/ts_equity_historical.py
openbb_tushare/utils/ts_equity_profile.py
openbb_tushare/utils/ts_equity_quote.py
openbb_tushare/utils/ts_equity_search.py
openbb_tushare/utils/ts_helpers.py
openbb_tushare/utils/ts_historical_dividends.py
openbb_tushare/utils/ts_income_statement.py
openbb_tushare-1.0.0.dist-info/entry_points.txt
openbb_tushare-1.0.0.dist-info/LICENSE
openbb_tushare-1.0.0.dist-info/METADATA
openbb_tushare-1.0.0.dist-info/WHEEL
openbb_tushare-1.0.0.dist-info/RECORD
