Metadata-Version: 2.3
Name: openbb-tushare
Version: 1.0.0
Summary: OpenBB extension for Tushare
License: AGPL-3.0-only
Author: Roger Ye
Author-email: shugaoye@yahoo.com
Requires-Python: >=3.9.21,<3.13
Classifier: License :: OSI Approved :: GNU Affero General Public License v3
Classifier: Programming Language :: Python :: 3
Classifier: Programming Language :: Python :: 3.10
Classifier: Programming Language :: Python :: 3.11
Classifier: Programming Language :: Python :: 3.12
Requires-Dist: chinese_calendar (>=1.10.0,<2.0.0)
Requires-Dist: mysharelib (>=1.0.1,<2.0.0)
Requires-Dist: openbb-core (>=1.4.7,<2.0.0)
Requires-Dist: tushare (>=1.4.21,<2.0.0)
